MANIFEST.in
README.rst
setup.py
cg/__init__.py
cg/_cg.pxd
cg/_cgGL.pxd
cg/_gl.pxd
cg/bridge.c
cg/bridge.pyx
cg/context.py
cg/errors.py
cg/openglinclude.h
cg/parameter.py
cg/utils.py
cg/effect/__init__.py
cg/effect/pass_.py
cg/effect/technique.py
python_cg.egg-info/PKG-INFO
python_cg.egg-info/SOURCES.txt
python_cg.egg-info/dependency_links.txt
python_cg.egg-info/requires.txt
python_cg.egg-info/top_level.txt