Metadata-Version: 1.1
Name: python-cg
Version: 0.1.3
Summary: Python wrapper for NVidia Cg Toolkit
Home-page: https://github.com/jstasiak/python-cg
Author: Jakub Stasiak
Author-email: jakub@stasiak.at
License: MIT
Platform: unix
Platform: linux
Platform: os x
Classifier: Development Status :: 3 - Alpha
Classifier: Intended Audience :: Developers
Classifier: License :: OSI Approved :: MIT License
Classifier: Operating System :: MacOS :: MacOS X
Classifier: Operating System :: POSIX :: Linux
Classifier: Programming Language :: Python
Classifier: Programming Language :: Python :: 2.6
Classifier: Programming Language :: Python :: 2.7
Classifier: Programming Language :: Python :: 3.2
Classifier: Programming Language :: Python :: 3.3
Classifier: Programming Language :: Python :: Implementation :: CPython
Classifier: Topic :: Multimedia :: Graphics :: 3D Rendering
Classifier: Topic :: Software Development :: Libraries :: Python Modules
